alinolreport/__init__.py
alinolreport/report.py
alinolreport-0.1.0.dist-info/METADATA
alinolreport-0.1.0.dist-info/WHEEL
alinolreport-0.1.0.dist-info/top_level.txt
alinolreport-0.1.0.dist-info/RECORD
