Metadata-Version: 2.4
Name: alinolreport
Version: 0.1.0
Summary: alinol is reporter for channel and group massage
Home-page: https://github.com/imramoxs/alinolreport
Author: ramox
Author-email: actramox@gmail.com
Classifier: Programming Language :: Python :: 3
Classifier: License :: OSI Approved :: MIT License
Classifier: Operating System :: OS Independent
Requires-Python: >=3.7
Requires-Dist: telethon>=1.25.0
Dynamic: author
Dynamic: author-email
Dynamic: classifier
Dynamic: description
Dynamic: description-content-type
Dynamic: home-page
Dynamic: requires-dist
Dynamic: requires-python
Dynamic: summary
